notebooks/advanced.ipynb
notebooks/examples.ipynb
notebooks/tutorial.ipynb
sickle_scope/__init__.py
sickle_scope/analyser.py
sickle_scope/cli.py
sickle_scope/ml_models.py
sickle_scope/utils.py
sickle_scope/visualiser.py
sickle_scope/data/hbb_variants.json
sickle_scope-0.1.0.dist-info/licenses/LICENSE
tests/__init__.py
tests/test_analyser.py
tests/test_cli.py
tests/test_integration.py
tests/test_visualiser.py
tests/sample_data/hbb_variants.csv
tests/sample_data/invalid_data.csv
tests/sample_data/test_variants.csv
sickle_scope-0.1.0.dist-info/METADATA
sickle_scope-0.1.0.dist-info/WHEEL
sickle_scope-0.1.0.dist-info/entry_points.txt
sickle_scope-0.1.0.dist-info/top_level.txt
sickle_scope-0.1.0.dist-info/RECORD
