Metadata-Version: 2.4
Name: sickle-scope
Version: 0.1.0
Summary: A genomic analysis tool for sickle cell disease variants
Home-page: https://github.com/talhahzubayer/sickle-scope
Author: Talhah Zubayer
Author-email: Talhah Zubayer <talhahzubayer101@gmail.com>
License: MIT License
Project-URL: Homepage, https://github.com/talhahzubayer/sickle-scope
Project-URL: Bug Reports, https://github.com/talhahzubayer/sickle-scope/issues
Project-URL: Source, https://github.com/talhahzubayer/sickle-scope
Classifier: Development Status :: 3 - Alpha
Classifier: Intended Audience :: Healthcare Industry
Classifier: Intended Audience :: Science/Research
Classifier: Topic :: Scientific/Engineering :: Bio-Informatics
Classifier: Topic :: Scientific/Engineering :: Medical Science Apps.
Classifier: Programming Language :: Python :: 3
Classifier: Programming Language :: Python :: 3.9
Classifier: Programming Language :: Python :: 3.10
Classifier: Programming Language :: Python :: 3.11
Classifier: Operating System :: OS Independent
Requires-Python: >=3.9
License-File: LICENSE
Requires-Dist: click>=8.0.0
Requires-Dist: pandas>=1.3.0
Requires-Dist: numpy>=1.21.0
Requires-Dist: matplotlib>=3.4.0
Requires-Dist: seaborn>=0.11.0
Requires-Dist: plotly>=5.0.0
Requires-Dist: scipy>=1.7.0
Requires-Dist: scikit-learn>=1.0.0
Requires-Dist: joblib>=1.0.0
Provides-Extra: dev
Requires-Dist: pytest>=6.0; extra == "dev"
Requires-Dist: pytest-cov>=2.0; extra == "dev"
Requires-Dist: black>=21.0; extra == "dev"
Requires-Dist: flake8>=3.9; extra == "dev"
Provides-Extra: notebook
Requires-Dist: jupyter>=1.0.0; extra == "notebook"
Requires-Dist: ipykernel>=6.0.0; extra == "notebook"
Dynamic: author
Dynamic: home-page
Dynamic: license-file
Dynamic: requires-python
